num_agents/__init__.py
num_agents/cli.py
num_agents/core.py
num_agents/cli/workflow_commands.py
num_agents/composer/__init__.py
num_agents/composer/composer.py
num_agents/composer/system_composer.py
num_agents/dashboard/__init__.py
num_agents/dashboard/app.py
num_agents/dashboard/components/__init__.py
num_agents/dashboard/components/agent_view.py
num_agents/dashboard/components/graph_view.py
num_agents/dashboard/components/memory_view.py
num_agents/dashboard/components/metrics_view.py
num_agents/dashboard/components/render_errors.py
num_agents/dashboard/components/render_events.py
num_agents/dashboard/components/render_node_performance.py
num_agents/dashboard/components/trace_view.py
num_agents/dashboard/data_providers/__init__.py
num_agents/dashboard/data_providers/agent_data_provider.py
num_agents/dashboard/data_providers/agent_provider.py
num_agents/dashboard/data_providers/event_provider.py
num_agents/dashboard/data_providers/graph_provider.py
num_agents/dashboard/data_providers/log_provider.py
num_agents/dashboard/data_providers/memory_provider.py
num_agents/dashboard/data_providers/metrics_provider.py
num_agents/dashboard/data_providers/trace_provider.py
num_agents/dashboard/utils/__init__.py
num_agents/dashboard/utils/export.py
num_agents/dashboard/utils/interactivity.py
num_agents/dashboard/utils/styling.py
num_agents/dashboard/utils/visualization.py
num_agents/dashboard/utils/visualizations.py
num_agents/eventbus/__init__.py
num_agents/eventbus/event.py
num_agents/eventbus/event_bus_node.py
num_agents/eventbus/eventbus.py
num_agents/eventbus/utils.py
num_agents/flow/__init__.py
num_agents/flow/conditional_flow.py
num_agents/flow/parallel_flow.py
num_agents/graph/__init__.py
num_agents/graph/logical_graph.py
num_agents/introspection/__init__.py
num_agents/introspection/adaptive_flow.py
num_agents/introspection/agent_introspector.py
num_agents/memory/entity_knowledge_base.py
num_agents/nodes/__init__.py
num_agents/nodes/api_node.py
num_agents-0.1.2.dist-info/METADATA
num_agents-0.1.2.dist-info/WHEEL
num_agents-0.1.2.dist-info/entry_points.txt
num_agents-0.1.2.dist-info/licenses/LICENSE
num_agents-0.1.2.dist-info/RECORD
